Metadata-Version: 2.1
Name: frauddetection-task
Version: 0.0.2
Summary: Technical task anamoly detection
Home-page: https://bitbucket.org/srijithm7_bb/fraudtransactiondetection/
Author: Srijith M
Author-email: srijithm7@gmail.com
License: UNKNOWN
Platform: UNKNOWN
Classifier: Programming Language :: Python :: 3
Classifier: License :: OSI Approved :: MIT License
Classifier: Operating System :: OS Independent
Requires-Python: >=3.6
